README.md
setup.py
XmindToTestlink/__init__.py
XmindToTestlink/check_xmind.py
XmindToTestlink/chipcase_restructure.py
XmindToTestlink/css.py
XmindToTestlink/dict_to_json.py
XmindToTestlink/dict_to_xml.py
XmindToTestlink/main.py
XmindToTestlink/markdown_to_dict.py
XmindToTestlink/preprocess.py
XmindToTestlink/read_xml.py
XmindToTestlink/rexmind.py
XmindToTestlink/xmind_to_dict.py
XmindToTestlink/xmind_to_obsidian.py
XmindToTestlink/xml_update.py
XmindToTestlink/zip_need.py
XmindToTestlink.egg-info/PKG-INFO
XmindToTestlink.egg-info/SOURCES.txt
XmindToTestlink.egg-info/dependency_links.txt
XmindToTestlink.egg-info/entry_points.txt
XmindToTestlink.egg-info/top_level.txt