Metadata-Version: 1.0
Name: XmindToTestlink
Version: 1.6.1
Summary: Convert xmindzen to TestLink xml
Home-page: https://github.com/DancePerth/XmindToTestlink
Author: DancePerth
Author-email: 28daysinperth@gmail.com
License: UNKNOWN
Keywords: xmind testlink import converter testing testcase requirement
Platform: UNKNOWN
